yerkes/__init__.py
yerkes/base.py
yerkes/cli.py
yerkes/palettes.py
yerkes-0.1.1.dist-info/METADATA
yerkes-0.1.1.dist-info/RECORD
yerkes-0.1.1.dist-info/WHEEL
yerkes-0.1.1.dist-info/entry_points.txt
yerkes-0.1.1.dist-info/top_level.txt
