Metadata-Version: 2.1
Name: yerkes
Version: 0.1.1
Summary: Interactive color palettes in Altair.
Home-page: https://github.com/zsailer/yerkes
Author: Zach Sailer
Author-email: zachsailer@gmail.com
License: MIT license
Keywords: yerkes
Platform: UNKNOWN
Classifier: Development Status :: 2 - Pre-Alpha
Classifier: Intended Audience :: Developers
Classifier: License :: OSI Approved :: MIT License
Classifier: Natural Language :: English
Classifier: Programming Language :: Python :: 2
Classifier: Programming Language :: Python :: 2.7
Classifier: Programming Language :: Python :: 3
Classifier: Programming Language :: Python :: 3.4
Classifier: Programming Language :: Python :: 3.5
Classifier: Programming Language :: Python :: 3.6
Requires-Dist: Click (>=6.0)
Requires-Dist: altair (>=0.2.1)
